claude_statusline/__init__.py
claude_statusline/__main__.py
claude_statusline/cli/__init__.py
claude_statusline/cli/statusline.py
claude_statusline/cli/token_graph.py
claude_statusline/core/__init__.py
claude_statusline/core/colors.py
claude_statusline/core/config.py
claude_statusline/core/git.py
claude_statusline/core/state.py
claude_statusline/formatters/__init__.py
claude_statusline/formatters/time.py
claude_statusline/formatters/tokens.py
claude_statusline/graphs/__init__.py
claude_statusline/graphs/renderer.py
claude_statusline/graphs/statistics.py
cc_statusline-1.0.2.dist-info/METADATA
cc_statusline-1.0.2.dist-info/WHEEL
cc_statusline-1.0.2.dist-info/entry_points.txt
cc_statusline-1.0.2.dist-info/RECORD
