Metadata-Version: 2.4
Name: cc-statusline
Version: 1.0.2
Summary: Custom status line and token visualization toolkit for Claude Code
Project-URL: Homepage, https://github.com/luongnv89/claude-statusline
Project-URL: Documentation, https://github.com/luongnv89/claude-statusline#readme
Project-URL: Repository, https://github.com/luongnv89/claude-statusline
Project-URL: Issues, https://github.com/luongnv89/claude-statusline/issues
Author-email: Nguyen Luong <luongnv89@gmail.com>
License: MIT
Keywords: claude,claude-code,cli,statusline,terminal,tokens
Classifier: Development Status :: 4 - Beta
Classifier: Environment :: Console
Classifier: Intended Audience :: Developers
Classifier: License :: OSI Approved :: MIT License
Classifier: Operating System :: OS Independent
Classifier: Programming Language :: Python :: 3
Classifier: Programming Language :: Python :: 3.9
Classifier: Programming Language :: Python :: 3.10
Classifier: Programming Language :: Python :: 3.11
Classifier: Programming Language :: Python :: 3.12
Classifier: Programming Language :: Python :: 3.13
Classifier: Topic :: Software Development :: Libraries :: Python Modules
Classifier: Topic :: Utilities
Requires-Python: >=3.9
Provides-Extra: dev
Requires-Dist: build>=1.0.0; extra == 'dev'
Requires-Dist: mypy>=1.7.0; extra == 'dev'
Requires-Dist: pytest-cov>=4.1.0; extra == 'dev'
Requires-Dist: pytest>=7.4.0; extra == 'dev'
Requires-Dist: ruff>=0.1.0; extra == 'dev'
Requires-Dist: twine>=4.0.0; extra == 'dev'
